pyvista4dolfinx/__init__.py
pyvista4dolfinx/gather.py
pyvista4dolfinx/misc.py
pyvista4dolfinx/plot.py
pyvista4dolfinx/safeplotter.py
pyvista4dolfinx-0.10.2.dist-info/METADATA
pyvista4dolfinx-0.10.2.dist-info/WHEEL
pyvista4dolfinx-0.10.2.dist-info/top_level.txt
pyvista4dolfinx-0.10.2.dist-info/RECORD
