Metadata-Version: 2.4
Name: pyvista4dolfinx
Version: 0.10.2
Summary: Re-introduction of a simple plot function for Dolfinx.
Author-email: "Stein K.F. Stoter" <k.f.s.stoter@tue.nl>
Maintainer-email: "Stein K.F. Stoter" <k.f.s.stoter@tue.nl>
Project-URL: Documentation, https://fenicsx4flow.gitlab.io/pyvista4dolfinx
Project-URL: Repository, https://gitlab.com/fenicsx4flow/pyvista4dolfinx
Keywords: dolfinx,FEniCSx,pyvista,plotting
Classifier: Development Status :: 4 - Beta
Classifier: Programming Language :: Python
Requires-Python: >=3.8
Requires-Dist: pyvista>0.45.0
Requires-Dist: pyvistaqt>0.11.0
